MANIFEST.in
README.rst
setup.py
KiTT.egg-info/PKG-INFO
KiTT.egg-info/SOURCES.txt
KiTT.egg-info/dependency_links.txt
KiTT.egg-info/entry_points.txt
KiTT.egg-info/not-zip-safe
KiTT.egg-info/requires.txt
KiTT.egg-info/top_level.txt
etc/kitt_config.json
etc/kitt_gestures.json
kitt/__init__.py
kitt/actions.py
kitt/daemon.py
kitt/kitt.py
kitt/listener.py
kitt/plugin_dbus.py
kitt/plugin_wnck.py
kitt/plugin_xlib.py