Metadata-Version: 1.0
Name: KiTT
Version: 1.1
Summary: Kivy Touch Tool
Home-page: http://m0g.net/kitt/
Author: Bernard `Guyzmo` Pratz
Author-email: kitt@m0g.net
License: GPLv3
Keywords: multitouch gesture management tool
Platform: UNKNOWN
